pyxcsao/__init__.py
pyxcsao/crosscorrelate.py
pyxcsao/data.py
pyxcsao/grid.py
PyXCSAO-0.2.dist-info/LICENSE
PyXCSAO-0.2.dist-info/METADATA
PyXCSAO-0.2.dist-info/WHEEL
PyXCSAO-0.2.dist-info/top_level.txt
PyXCSAO-0.2.dist-info/RECORD
