Metadata-Version: 2.1
Name: PyXCSAO
Version: 0.2
Summary: Replicates functionality of IRAF XCSAO
Home-page: https://github.com/mkounkel/pyxcsao
Author: Marina Kounkel
Author-email: marina.kounkel@vanderbilt.edu
Classifier: Programming Language :: Python :: 3
Classifier: License :: OSI Approved :: MIT License
Classifier: Operating System :: OS Independent
Requires-Python: >=3.6
License-File: LICENSE
Requires-Dist: astropy
Requires-Dist: numpy
Requires-Dist: scipy
Requires-Dist: specutils
Requires-Dist: PyAstronomy
